jikkensol/__init__.py
jikkensol/hello.py
jikkensol/jikkensol.py
jikkensol/test.py
jikkensol/files/songs.txt
jikkensol-0.0.10.dist-info/DESCRIPTION.rst
jikkensol-0.0.10.dist-info/METADATA
jikkensol-0.0.10.dist-info/RECORD
jikkensol-0.0.10.dist-info/WHEEL
jikkensol-0.0.10.dist-info/entry_points.txt
jikkensol-0.0.10.dist-info/metadata.json
jikkensol-0.0.10.dist-info/top_level.txt
