Metadata-Version: 2.0
Name: jikkensol
Version: 0.0.10
Summary: jikken package
Home-page: http://www.solima.net/
Author: solima
Author-email: UNKNOWN
License: GPL
Keywords: jikken package
Platform: UNKNOWN
